syncord/__init__.py
syncord/blacklist.py
syncord/bot.py
syncord/components.py
syncord/emb.py
syncord/enums.py
syncord/errors.py
syncord/logs.py
syncord/sql.py
syncord/times.py
syncord/utils.py
syncord/cogs/blacklist.py
syncord/cogs/help.py
syncord/cogs/status_changer.py
syncord/cogs/dpy/blacklist_setup.py
syncord/cogs/dpy/help_setup.py
syncord/cogs/dpy/status_changer_setup.py
syncord/cogs/pyc/blacklist_setup.py
syncord/cogs/pyc/help_setup.py
syncord/cogs/pyc/status_changer_setup.py
syncord/internal/__init__.py
syncord/internal/colors.py
syncord/internal/config.py
syncord/internal/embed_templates.py
syncord/internal/ready_style.py
syncord/internal/translation.py
syncord/internal/dc/__init__.py
syncord/internal/dc/dc_imports.py
syncord/internal/language/de.json
syncord/internal/language/en.json
syncord/internal/language/languages.py
syncord-0.5.2.dist-info/LICENSE
syncord-0.5.2.dist-info/METADATA
syncord-0.5.2.dist-info/WHEEL
syncord-0.5.2.dist-info/top_level.txt
syncord-0.5.2.dist-info/RECORD
