Metadata-Version: 2.1
Name: syncord
Version: 0.5.2
Summary: An easy-to-use extension for Discord.py and Pycord
Author: ace
License: MIT
Project-URL: GitHub, https://github.com/sqiuwsqjjsxsajisaj/syncord
Keywords: discord,pycord,py-cord,discord.py
Classifier: Development Status :: 5 - Production/Stable
Classifier: License :: OSI Approved :: MIT License
Classifier: Intended Audience :: Developers
Classifier: Operating System :: OS Independent
Classifier: Topic :: Software Development :: Libraries
Classifier: Topic :: Software Development :: Libraries :: Python Modules
Classifier: Topic :: Utilities
Classifier: Programming Language :: Python :: 3.9
Classifier: Programming Language :: Python :: 3.10
Classifier: Programming Language :: Python :: 3.11
Requires-Python: >=3.9
License-File: LICENSE
Requires-Dist: aiohttp
Requires-Dist: colorama
Requires-Dist: aiosqlite
Requires-Dist: python-dotenv
Provides-Extra: dev
Requires-Dist: pre-commit ; extra == 'dev'
Requires-Dist: pytest ; extra == 'dev'
Requires-Dist: pytest-asyncio ; extra == 'dev'
Provides-Extra: docs
